natural_language_test/test1.py
natural_language_test/test2.py
natural_language_test-0.0.0.2.dist-info/METADATA
natural_language_test-0.0.0.2.dist-info/WHEEL
natural_language_test-0.0.0.2.dist-info/top_level.txt
natural_language_test-0.0.0.2.dist-info/RECORD
