Metadata-Version: 2.1
Name: natural-language-test
Version: 0.0.0.2
Summary: My First Test Package
Home-page: https://lingua.blog.me/…
Author: Jiho Yoon
Author-email: j5i3h8o8@gmail.com
License: MIT
Requires-Python: >=3
